friendsep/__init__.py
friendsep/friendsep.py
friendsep-0.0.3.dist-info/METADATA
friendsep-0.0.3.dist-info/RECORD
friendsep-0.0.3.dist-info/WHEEL
friendsep-0.0.3.dist-info/entry_points.txt
friendsep-0.0.3.dist-info/top_level.txt
