Metadata-Version: 2.1
Name: friendsep
Version: 0.0.3
Summary: A simple command line tool to watch a random episode of F.R.I.E.N.D.S
Home-page: https://github.com/VinitraMk/friendsep
Author: VinitraMk
Author-email: vinitramk@gmail.com
License: UNKNOWN
Platform: UNKNOWN
Classifier: Development Status :: 4 - Beta
Classifier: Intended Audience :: Developers
Classifier: Operating System :: POSIX
Classifier: Programming Language :: Python :: 3
Classifier: License :: OSI Approved :: MIT License
